setup.py
pyperseus_treebank/__init__.py
pyperseus_treebank/base.py
pyperseus_treebank/latin.py
pyperseus_treebank.egg-info/PKG-INFO
pyperseus_treebank.egg-info/SOURCES.txt
pyperseus_treebank.egg-info/dependency_links.txt
pyperseus_treebank.egg-info/requires.txt
pyperseus_treebank.egg-info/top_level.txt