Metadata-Version: 1.0
Name: pyperseus-treebank
Version: 0.0.1
Summary: Perseus XML Treebank Parser
Home-page: https://github.com/ponteineptique/pyperseus-treebank
Author: Thibault Clerice
Author-email: leponteineptique@gmail.com
License: GNU GPL v2
Platform: UNKNOWN
